special_k/__init__.py
special_k/api.py
special_k/check_gpg_keys/__init__.py
special_k/check_gpg_keys/__main__.py
special_k/check_gpg_keys/verify_expiry.py
special_k/exceptions.py
special_k/model_interface.py
special_k/model_metadata/__init__.py
special_k/model_metadata/metadata_format_v3.py
special_k/pytest.ini
special_k/serializable_model.py
special_k/serializers/__init__.py
special_k/serializers/base.py
special_k/serializers/base_serializers.py
special_k/serializers/registry.py
special_k/serializers/utils.py
special_k/signing.py
special_k/tests/__init__.py
special_k/tests/fake_keys/__init__.py
special_k/tests/fake_keys/keyname-to-fingerprint.json
special_k/tests/fake_keys/my.txt.asc
special_k/tests/fake_keys/testing.pub.asc
special_k/tests/fake_keys/testing.secret.asc
special_k/tests/fake_keys/trustdb.txt
special_k/tests/test_model_interface.py
special_k/tests/test_model_serialization.py
special_k/tests/test_registry.py
special_k/tests/test_serialization_helpers.py
special_k/tests/test_serializers.py
special_k/tests/test_signing.py
special_k/tests/test_verifiable_stream.py
special_k/tests/utils.py
special_k/utils.py
special_k/verifiable_stream.py
special_k-0.1.1.dist-info/LICENSE.md
special_k-0.1.1.dist-info/WHEEL
special_k-0.1.1.dist-info/METADATA
special_k-0.1.1.dist-info/RECORD
